README.rst
setup.py
cmml/DecisionTree.py
cmml/__init__.py
cmml/adaboost.py
cmml/apriori.py
cmml/bayes.py
cmml/decisionTreePlot.py
cmml/decisiontree.py
cmml/fpGrowth.py
cmml/kMeans.py
cmml/kNN.py
cmml/logistic.py
cmml/pca.py
cmml/randomForest.py
cmml/regTrees.py
cmml/regress.py
cmml/regression.py
cmml/svdRecommend.py
cmml/svm-simple.py
cmml.egg-info/PKG-INFO
cmml.egg-info/SOURCES.txt
cmml.egg-info/dependency_links.txt
cmml.egg-info/top_level.txt
cmml/kmeans/__init__.py
cmml/kmeans/kMeans.py
cmml/kmeans/kMeansSklearn.py