Metadata-Version: 1.2
Name: cmml
Version: 1.1.0
Summary: 机器学习
Home-page: http://github.com/Mark110
Author: 曹明
Author-email: 18911205637@163.com
Maintainer: 曹明
Maintainer-email: 18911205637@163.com
License: BSD License
Platform: UNKNOWN
Classifier: Operating System :: OS Independent
Classifier: Intended Audience :: Developers
Classifier: License :: OSI Approved :: BSD License
Classifier: Programming Language :: Python
Classifier: Programming Language :: Python :: Implementation
Classifier: Programming Language :: Python :: 2
Classifier: Programming Language :: Python :: 2.7
Classifier: Programming Language :: Python :: 3
Classifier: Programming Language :: Python :: 3.4
Classifier: Programming Language :: Python :: 3.5
Classifier: Programming Language :: Python :: 3.6
Classifier: Topic :: Software Development :: Libraries
